radvis/__init__.py
radvis/image/__init__.py
radvis/image/instantiate.py
radvis/image/rad_dicom_image.py
radvis/image/rad_image.py
radvis/image/rad_nifti_image.py
radvis/image/rad_numpy_image.py
radvis/mesh/__init__.py
radvis/mesh/compute_mesh.py
radvis/mesh/rad_mesh.py
radvis/processing/__init__.py
radvis/processing/image.py
radvis/processing/registration.py
radvis/visualize/__init__.py
radvis/visualize/rad_slicer.py
radvis/visualize/rad_slicer_group.py
tests/__init__.py
tests/mocks/__init__.py
tests/mocks/mock_rad_image.py
tests/test_image/__init__.py
tests/test_image/test_instantiate.py
tests/test_mesh/__init__.py
tests/test_mesh/test_compute_mesh.py
tests/test_processing/__init__.py
tests/test_processing/test_image.py
tests/test_visualize/__init__.py
tests/test_visualize/test_rad_slicer.py
radvis-0.3.0.dist-info/LICENSE
radvis-0.3.0.dist-info/METADATA
radvis-0.3.0.dist-info/WHEEL
radvis-0.3.0.dist-info/top_level.txt
radvis-0.3.0.dist-info/RECORD
