Metadata-Version: 2.1
Name: radvis
Version: 0.3.0
Summary: A visualization tool for medical images
Home-page: https://github.com/medlee-code/RadVis
Author: Matthew lee
Author-email: matthewlee@medlee.io
Requires-Python: >=3.10
License-File: LICENSE
Requires-Dist: scikit-image (==0.20.0)
Requires-Dist: pydicom (==2.3.1)
Requires-Dist: nibabel (==5.1.0)
Requires-Dist: matplotlib (==3.7.1)
